<?xml version="1.0" ?>
<annotation>
<folder>KITTI</folder>
<filename>000558.png</filename>
<source>
<database>The KITTI Database</database>
<annotation>KITTI</annotation>
</source>
<size>
<width>1241</width>
<height>376</height>
<depth>3</depth>
</size>
<object>
<name>Car</name>
<bndbox>
<xmin>572</xmin>
<ymin>174</ymin>
<xmax>611</xmax>
<ymax>209</ymax>
</bndbox>
</object>
<object>
<name>Car</name>
<bndbox>
<xmin>0</xmin>
<ymin>193</ymin>
<xmax>336</xmax>
<ymax>375</ymax>
</bndbox>
</object>
<object>
<name>Car</name>
<bndbox>
<xmin>103</xmin>
<ymin>187</ymin>
<xmax>290</xmax>
<ymax>266</ymax>
</bndbox>
</object>
<object>
<name>Car</name>
<bndbox>
<xmin>359</xmin>
<ymin>187</ymin>
<xmax>467</xmax>
<ymax>252</ymax>
</bndbox>
</object>
<object>
<name>Car</name>
<bndbox>
<xmin>305</xmin>
<ymin>181</ymin>
<xmax>388</xmax>
<ymax>227</ymax>
</bndbox>
</object>
<object>
<name>Car</name>
<bndbox>
<xmin>417</xmin>
<ymin>179</ymin>
<xmax>487</xmax>
<ymax>225</ymax>
</bndbox>
</object>
<object>
<name>Car</name>
<bndbox>
<xmin>491</xmin>
<ymin>158</ymin>
<xmax>540</xmax>
<ymax>207</ymax>
</bndbox>
</object>
<object>
<name>Car</name>
<bndbox>
<xmin>539</xmin>
<ymin>167</ymin>
<xmax>560</xmax>
<ymax>191</ymax>
</bndbox>
</object>
<object>
<name>Car</name>
<bndbox>
<xmin>0</xmin>
<ymin>180</ymin>
<xmax>161</xmax>
<ymax>261</ymax>
</bndbox>
</object>
</annotation>
