<?xml version="1.0" ?>
<annotation>
<folder>KITTI</folder>
<filename>000704.png</filename>
<source>
<database>The KITTI Database</database>
<annotation>KITTI</annotation>
</source>
<size>
<width>1242</width>
<height>375</height>
<depth>3</depth>
</size>
<object>
<name>Car</name>
<bndbox>
<xmin>750</xmin>
<ymin>163</ymin>
<xmax>1068</xmax>
<ymax>365</ymax>
</bndbox>
</object>
<object>
<name>Car</name>
<bndbox>
<xmin>0</xmin>
<ymin>207</ymin>
<xmax>285</xmax>
<ymax>374</ymax>
</bndbox>
</object>
<object>
<name>Car</name>
<bndbox>
<xmin>658</xmin>
<ymin>173</ymin>
<xmax>712</xmax>
<ymax>218</ymax>
</bndbox>
</object>
<object>
<name>Car</name>
<bndbox>
<xmin>702</xmin>
<ymin>152</ymin>
<xmax>744</xmax>
<ymax>186</ymax>
</bndbox>
</object>
</annotation>
