<?xml version="1.0" ?>
<annotation>
<folder>KITTI</folder>
<filename>002112.png</filename>
<source>
<database>The KITTI Database</database>
<annotation>KITTI</annotation>
</source>
<size>
<width>1242</width>
<height>375</height>
<depth>3</depth>
</size>
<object>
<name>Car</name>
<bndbox>
<xmin>0</xmin>
<ymin>188</ymin>
<xmax>215</xmax>
<ymax>374</ymax>
</bndbox>
</object>
<object>
<name>Car</name>
<bndbox>
<xmin>351</xmin>
<ymin>183</ymin>
<xmax>458</xmax>
<ymax>255</ymax>
</bndbox>
</object>
<object>
<name>Cyclist</name>
<bndbox>
<xmin>524</xmin>
<ymin>175</ymin>
<xmax>542</xmax>
<ymax>216</ymax>
</bndbox>
</object>
<object>
<name>Cyclist</name>
<bndbox>
<xmin>541</xmin>
<ymin>176</ymin>
<xmax>558</xmax>
<ymax>214</ymax>
</bndbox>
</object>
<object>
<name>Car</name>
<bndbox>
<xmin>464</xmin>
<ymin>183</ymin>
<xmax>516</xmax>
<ymax>216</ymax>
</bndbox>
</object>
<object>
<name>Cyclist</name>
<bndbox>
<xmin>548</xmin>
<ymin>176</ymin>
<xmax>561</xmax>
<ymax>203</ymax>
</bndbox>
</object>
<object>
<name>Car</name>
<bndbox>
<xmin>631</xmin>
<ymin>176</ymin>
<xmax>657</xmax>
<ymax>197</ymax>
</bndbox>
</object>
<object>
<name>Car</name>
<bndbox>
<xmin>683</xmin>
<ymin>172</ymin>
<xmax>799</xmax>
<ymax>262</ymax>
</bndbox>
</object>
</annotation>
