<?xml version="1.0" ?>
<annotation>
<folder>KITTI</folder>
<filename>003479.png</filename>
<source>
<database>The KITTI Database</database>
<annotation>KITTI</annotation>
</source>
<size>
<width>1242</width>
<height>375</height>
<depth>3</depth>
</size>
<object>
<name>Car</name>
<bndbox>
<xmin>645</xmin>
<ymin>171</ymin>
<xmax>687</xmax>
<ymax>207</ymax>
</bndbox>
</object>
<object>
<name>Car</name>
<bndbox>
<xmin>673</xmin>
<ymin>179</ymin>
<xmax>728</xmax>
<ymax>220</ymax>
</bndbox>
</object>
<object>
<name>Car</name>
<bndbox>
<xmin>654</xmin>
<ymin>147</ymin>
<xmax>699</xmax>
<ymax>192</ymax>
</bndbox>
</object>
<object>
<name>Car</name>
<bndbox>
<xmin>774</xmin>
<ymin>176</ymin>
<xmax>857</xmax>
<ymax>221</ymax>
</bndbox>
</object>
<object>
<name>Car</name>
<bndbox>
<xmin>801</xmin>
<ymin>175</ymin>
<xmax>867</xmax>
<ymax>202</ymax>
</bndbox>
</object>
</annotation>
