<?xml version="1.0" ?>
<annotation>
<folder>KITTI</folder>
<filename>003503.png</filename>
<source>
<database>The KITTI Database</database>
<annotation>KITTI</annotation>
</source>
<size>
<width>1242</width>
<height>375</height>
<depth>3</depth>
</size>
<object>
<name>Car</name>
<bndbox>
<xmin>920</xmin>
<ymin>212</ymin>
<xmax>1241</xmax>
<ymax>374</ymax>
</bndbox>
</object>
<object>
<name>Car</name>
<bndbox>
<xmin>469</xmin>
<ymin>181</ymin>
<xmax>546</xmax>
<ymax>245</ymax>
</bndbox>
</object>
<object>
<name>Car</name>
<bndbox>
<xmin>678</xmin>
<ymin>186</ymin>
<xmax>787</xmax>
<ymax>269</ymax>
</bndbox>
</object>
<object>
<name>Car</name>
<bndbox>
<xmin>536</xmin>
<ymin>183</ymin>
<xmax>572</xmax>
<ymax>215</ymax>
</bndbox>
</object>
<object>
<name>Car</name>
<bndbox>
<xmin>646</xmin>
<ymin>180</ymin>
<xmax>687</xmax>
<ymax>215</ymax>
</bndbox>
</object>
</annotation>
