<?xml version="1.0" ?>
<annotation>
<folder>KITTI</folder>
<filename>004415.png</filename>
<source>
<database>The KITTI Database</database>
<annotation>KITTI</annotation>
</source>
<size>
<width>1242</width>
<height>375</height>
<depth>3</depth>
</size>
<object>
<name>Car</name>
<bndbox>
<xmin>600</xmin>
<ymin>156</ymin>
<xmax>630</xmax>
<ymax>189</ymax>
</bndbox>
</object>
<object>
<name>Car</name>
<bndbox>
<xmin>432</xmin>
<ymin>179</ymin>
<xmax>459</xmax>
<ymax>197</ymax>
</bndbox>
</object>
<object>
<name>Cyclist</name>
<bndbox>
<xmin>672</xmin>
<ymin>164</ymin>
<xmax>683</xmax>
<ymax>191</ymax>
</bndbox>
</object>
</annotation>
