<?xml version="1.0" ?>
<annotation>
<folder>KITTI</folder>
<filename>006111.png</filename>
<source>
<database>The KITTI Database</database>
<annotation>KITTI</annotation>
</source>
<size>
<width>1242</width>
<height>375</height>
<depth>3</depth>
</size>
<object>
<name>Car</name>
<bndbox>
<xmin>588</xmin>
<ymin>176</ymin>
<xmax>648</xmax>
<ymax>233</ymax>
</bndbox>
</object>
<object>
<name>Car</name>
<bndbox>
<xmin>679</xmin>
<ymin>175</ymin>
<xmax>726</xmax>
<ymax>213</ymax>
</bndbox>
</object>
<object>
<name>Car</name>
<bndbox>
<xmin>954</xmin>
<ymin>165</ymin>
<xmax>1027</xmax>
<ymax>194</ymax>
</bndbox>
</object>
<object>
<name>Car</name>
<bndbox>
<xmin>1010</xmin>
<ymin>154</ymin>
<xmax>1098</xmax>
<ymax>198</ymax>
</bndbox>
</object>
</annotation>
