<?xml version="1.0" ?>
<annotation>
<folder>KITTI</folder>
<filename>006290.png</filename>
<source>
<database>The KITTI Database</database>
<annotation>KITTI</annotation>
</source>
<size>
<width>1242</width>
<height>375</height>
<depth>3</depth>
</size>
<object>
<name>Car</name>
<bndbox>
<xmin>580</xmin>
<ymin>175</ymin>
<xmax>638</xmax>
<ymax>232</ymax>
</bndbox>
</object>
<object>
<name>Car</name>
<bndbox>
<xmin>664</xmin>
<ymin>177</ymin>
<xmax>699</xmax>
<ymax>206</ymax>
</bndbox>
</object>
<object>
<name>Car</name>
<bndbox>
<xmin>890</xmin>
<ymin>170</ymin>
<xmax>943</xmax>
<ymax>193</ymax>
</bndbox>
</object>
<object>
<name>Car</name>
<bndbox>
<xmin>928</xmin>
<ymin>161</ymin>
<xmax>988</xmax>
<ymax>195</ymax>
</bndbox>
</object>
</annotation>
