<?xml version="1.0" ?>
<annotation>
<folder>KITTI</folder>
<filename>006859.png</filename>
<source>
<database>The KITTI Database</database>
<annotation>KITTI</annotation>
</source>
<size>
<width>1242</width>
<height>375</height>
<depth>3</depth>
</size>
<object>
<name>Car</name>
<bndbox>
<xmin>227</xmin>
<ymin>192</ymin>
<xmax>316</xmax>
<ymax>243</ymax>
</bndbox>
</object>
<object>
<name>Car</name>
<bndbox>
<xmin>509</xmin>
<ymin>172</ymin>
<xmax>544</xmax>
<ymax>202</ymax>
</bndbox>
</object>
<object>
<name>Car</name>
<bndbox>
<xmin>439</xmin>
<ymin>162</ymin>
<xmax>486</xmax>
<ymax>198</ymax>
</bndbox>
</object>
<object>
<name>Car</name>
<bndbox>
<xmin>403</xmin>
<ymin>182</ymin>
<xmax>457</xmax>
<ymax>217</ymax>
</bndbox>
</object>
<object>
<name>Car</name>
<bndbox>
<xmin>327</xmin>
<ymin>187</ymin>
<xmax>391</xmax>
<ymax>223</ymax>
</bndbox>
</object>
<object>
<name>Cyclist</name>
<bndbox>
<xmin>329</xmin>
<ymin>176</ymin>
<xmax>364</xmax>
<ymax>232</ymax>
</bndbox>
</object>
<object>
<name>Pedestrian</name>
<bndbox>
<xmin>470</xmin>
<ymin>178</ymin>
<xmax>477</xmax>
<ymax>201</ymax>
</bndbox>
</object>
<object>
<name>Car</name>
<bndbox>
<xmin>1017</xmin>
<ymin>149</ymin>
<xmax>1241</xmax>
<ymax>247</ymax>
</bndbox>
</object>
<object>
<name>Car</name>
<bndbox>
<xmin>295</xmin>
<ymin>182</ymin>
<xmax>356</xmax>
<ymax>201</ymax>
</bndbox>
</object>
</annotation>
