<?xml version="1.0" ?>
<annotation>
<folder>KITTI</folder>
<filename>007407.png</filename>
<source>
<database>The KITTI Database</database>
<annotation>KITTI</annotation>
</source>
<size>
<width>1242</width>
<height>375</height>
<depth>3</depth>
</size>
<object>
<name>Car</name>
<bndbox>
<xmin>0</xmin>
<ymin>210</ymin>
<xmax>221</xmax>
<ymax>374</ymax>
</bndbox>
</object>
<object>
<name>Car</name>
<bndbox>
<xmin>470</xmin>
<ymin>185</ymin>
<xmax>565</xmax>
<ymax>243</ymax>
</bndbox>
</object>
<object>
<name>Cyclist</name>
<bndbox>
<xmin>723</xmin>
<ymin>177</ymin>
<xmax>752</xmax>
<ymax>244</ymax>
</bndbox>
</object>
<object>
<name>Car</name>
<bndbox>
<xmin>626</xmin>
<ymin>178</ymin>
<xmax>669</xmax>
<ymax>203</ymax>
</bndbox>
</object>
<object>
<name>Car</name>
<bndbox>
<xmin>821</xmin>
<ymin>150</ymin>
<xmax>916</xmax>
<ymax>192</ymax>
</bndbox>
</object>
<object>
<name>Cyclist</name>
<bndbox>
<xmin>728</xmin>
<ymin>168</ymin>
<xmax>770</xmax>
<ymax>261</ymax>
</bndbox>
</object>
</annotation>
